mezzanine_sermons
