Metadata-Version: 1.1
Name: mezzanine-sermons
Version: 0.1.6
Summary: A simple mezzanine app which facilitates the management and playing of sermons
Home-page: https://github.com/philipsouthwell/mezzanine-sermons
Author: Philip Southwell
Author-email: phil@zoothink.com
License: BSD License
Keywords: django,mezzanine
Platform: UNKNOWN
Classifier: Environment :: Web Environment
Classifier: Intended Audience :: Developers
Classifier: License :: OSI Approved :: BSD License
Classifier: Operating System :: OS Independent
Classifier: Programming Language :: Python
Classifier: Programming Language :: Python :: 3
Classifier: Programming Language :: Python :: 3.2
Classifier: Programming Language :: Python :: 3.3
Classifier: Programming Language :: Python :: 3.4
Classifier: Topic :: Internet :: WWW/HTTP
Classifier: Topic :: Internet :: WWW/HTTP :: Dynamic Content
